{
  "locked": false,
  "version": 2,
  "targets": {
    ".NETFramework,Version=v4.5": {
      "AutoMapper/4.1.0": {
        "type": "package",
        "frameworkAssemblies": [
          "Microsoft.CSharp",
          "mscorlib",
          "System",
          "System.Core"
        ],
        "compile": {
          "lib/net45/AutoMapper.dll": {}
        },
        "runtime": {
          "lib/net45/AutoMapper.dll": {}
        }
      }
    },
    ".NETFramework,Version=v4.0": {
      "AutoMapper/4.1.0": {
        "type": "package",
        "dependencies": {
          "Microsoft.Bcl": "1.1.9"
        },
        "frameworkAssemblies": [
          "Microsoft.CSharp",
          "mscorlib",
          "System",
          "System.Core"
        ],
        "compile": {
          "lib/net40/AutoMapper.dll": {}
        },
        "runtime": {
          "lib/net40/AutoMapper.dll": {}
        }
      },
      "Microsoft.Bcl/1.1.9": {
        "type": "package",
        "dependencies": {
          "Microsoft.Bcl.Build": "1.0.14"
        },
        "compile": {
          "lib/net40/System.IO.dll": {},
          "lib/net40/System.Runtime.dll": {},
          "lib/net40/System.Threading.Tasks.dll": {}
        },
        "runtime": {
          "lib/net40/System.IO.dll": {},
          "lib/net40/System.Runtime.dll": {},
          "lib/net40/System.Threading.Tasks.dll": {}
        }
      },
      "Microsoft.Bcl.Build/1.0.14": {
        "type": "package"
      }
    },
    ".NETFramework,Version=v4.5/win7-x86": {
      "AutoMapper/4.1.0": {
        "type": "package",
        "frameworkAssemblies": [
          "Microsoft.CSharp",
          "mscorlib",
          "System",
          "System.Core"
        ],
        "compile": {
          "lib/net45/AutoMapper.dll": {}
        },
        "runtime": {
          "lib/net45/AutoMapper.dll": {}
        }
      }
    },
    ".NETFramework,Version=v4.5/win7-x64": {
      "AutoMapper/4.1.0": {
        "type": "package",
        "frameworkAssemblies": [
          "Microsoft.CSharp",
          "mscorlib",
          "System",
          "System.Core"
        ],
        "compile": {
          "lib/net45/AutoMapper.dll": {}
        },
        "runtime": {
          "lib/net45/AutoMapper.dll": {}
        }
      }
    },
    ".NETFramework,Version=v4.0/win7-x86": {
      "AutoMapper/4.1.0": {
        "type": "package",
        "dependencies": {
          "Microsoft.Bcl": "1.1.9"
        },
        "frameworkAssemblies": [
          "Microsoft.CSharp",
          "mscorlib",
          "System",
          "System.Core"
        ],
        "compile": {
          "lib/net40/AutoMapper.dll": {}
        },
        "runtime": {
          "lib/net40/AutoMapper.dll": {}
        }
      },
      "Microsoft.Bcl/1.1.9": {
        "type": "package",
        "dependencies": {
          "Microsoft.Bcl.Build": "1.0.14"
        },
        "compile": {
          "lib/net40/System.IO.dll": {},
          "lib/net40/System.Runtime.dll": {},
          "lib/net40/System.Threading.Tasks.dll": {}
        },
        "runtime": {
          "lib/net40/System.IO.dll": {},
          "lib/net40/System.Runtime.dll": {},
          "lib/net40/System.Threading.Tasks.dll": {}
        }
      },
      "Microsoft.Bcl.Build/1.0.14": {
        "type": "package"
      }
    },
    ".NETFramework,Version=v4.0/win7-x64": {
      "AutoMapper/4.1.0": {
        "type": "package",
        "dependencies": {
          "Microsoft.Bcl": "1.1.9"
        },
        "frameworkAssemblies": [
          "Microsoft.CSharp",
          "mscorlib",
          "System",
          "System.Core"
        ],
        "compile": {
          "lib/net40/AutoMapper.dll": {}
        },
        "runtime": {
          "lib/net40/AutoMapper.dll": {}
        }
      },
      "Microsoft.Bcl/1.1.9": {
        "type": "package",
        "dependencies": {
          "Microsoft.Bcl.Build": "1.0.14"
        },
        "compile": {
          "lib/net40/System.IO.dll": {},
          "lib/net40/System.Runtime.dll": {},
          "lib/net40/System.Threading.Tasks.dll": {}
        },
        "runtime": {
          "lib/net40/System.IO.dll": {},
          "lib/net40/System.Runtime.dll": {},
          "lib/net40/System.Threading.Tasks.dll": {}
        }
      },
      "Microsoft.Bcl.Build/1.0.14": {
        "type": "package"
      }
    }
  },
  "libraries": {
    "AutoMapper/4.1.0": {
      "type": "package",
      "sha512": "PDag8anMYU0ZGHsPAsF8SY+Gj3JPPQ4Sm0PH4TCc4ktk56C4lCtt2WHlqR92/szFWo1L+50seVKOBiGyK06LhQ==",
      "files": [
        "AutoMapper.4.1.0.nupkg",
        "AutoMapper.4.1.0.nupkg.sha512",
        "AutoMapper.nuspec",
        "lib/dotnet/AutoMapper.dll",
        "lib/dotnet/AutoMapper.xml",
        "lib/MonoAndroid/AutoMapper.dll",
        "lib/MonoAndroid/AutoMapper.XML",
        "lib/MonoTouch/AutoMapper.dll",
        "lib/MonoTouch/AutoMapper.XML",
        "lib/net40/AutoMapper.dll",
        "lib/net40/AutoMapper.xml",
        "lib/net45/AutoMapper.dll",
        "lib/net45/AutoMapper.xml",
        "lib/portable-net45+win+wpa81+wp80+MonoAndroid10+Xamarin.iOS10+MonoTouch10/AutoMapper.dll",
        "lib/portable-net45+win+wpa81+wp80+MonoAndroid10+Xamarin.iOS10+MonoTouch10/AutoMapper.xml",
        "lib/sl50/AutoMapper.dll",
        "lib/sl50/AutoMapper.XML",
        "lib/win/AutoMapper.dll",
        "lib/win/AutoMapper.xml",
        "lib/wp80/AutoMapper.dll",
        "lib/wp80/AutoMapper.xml",
        "lib/wpa81/AutoMapper.dll",
        "lib/wpa81/AutoMapper.xml",
        "lib/Xamarin.iOS10/AutoMapper.dll",
        "lib/Xamarin.iOS10/AutoMapper.XML"
      ]
    },
    "Microsoft.Bcl/1.1.9": {
      "type": "package",
      "sha512": "USQ55innJy8K+tAXvVa1O8dUTp2s7pmJ5cJj6Tl02HtGc2xBDj0P2QH5620HbGXIWKWYhydoeQF8Rm/JRDBGhw==",
      "files": [
        "content/monoandroid/_._",
        "content/monotouch/_._",
        "content/net45/_._",
        "content/portable-net45+win8+wp8+wpa81/_._",
        "content/portable-net45+win8+wpa81/_._",
        "content/portable-net451+win81/_._",
        "content/portable-net451+win81+wpa81/_._",
        "content/portable-win81+wp81+wpa81/_._",
        "content/sl4/_._",
        "content/sl5/_._",
        "content/win8/_._",
        "content/wp8/_._",
        "content/wpa81/_._",
        "lib/monoandroid/_._",
        "lib/monotouch/_._",
        "lib/net40/ensureRedirect.xml",
        "lib/net40/System.IO.dll",
        "lib/net40/System.IO.xml",
        "lib/net40/System.Runtime.dll",
        "lib/net40/System.Runtime.xml",
        "lib/net40/System.Threading.Tasks.dll",
        "lib/net40/System.Threading.Tasks.xml",
        "lib/net45/_._",
        "lib/portable-net40+sl4+win8/ensureRedirect.xml",
        "lib/portable-net40+sl4+win8/System.IO.dll",
        "lib/portable-net40+sl4+win8/System.IO.xml",
        "lib/portable-net40+sl4+win8/System.Runtime.dll",
        "lib/portable-net40+sl4+win8/System.Runtime.xml",
        "lib/portable-net40+sl4+win8/System.Threading.Tasks.dll",
        "lib/portable-net40+sl4+win8/System.Threading.Tasks.xml",
        "lib/portable-net40+sl4+win8+wp71+wpa81/ensureRedirect.xml",
        "lib/portable-net40+sl4+win8+wp71+wpa81/System.IO.dll",
        "lib/portable-net40+sl4+win8+wp71+wpa81/System.IO.xml",
        "lib/portable-net40+sl4+win8+wp71+wpa81/System.Runtime.dll",
        "lib/portable-net40+sl4+win8+wp71+wpa81/System.Runtime.xml",
        "lib/portable-net40+sl4+win8+wp71+wpa81/System.Threading.Tasks.dll",
        "lib/portable-net40+sl4+win8+wp71+wpa81/System.Threading.Tasks.xml",
        "lib/portable-net40+sl4+win8+wp8+wpa81/ensureRedirect.xml",
        "lib/portable-net40+sl4+win8+wp8+wpa81/System.IO.dll",
        "lib/portable-net40+sl4+win8+wp8+wpa81/System.IO.xml",
        "lib/portable-net40+sl4+win8+wp8+wpa81/System.Runtime.dll",
        "lib/portable-net40+sl4+win8+wp8+wpa81/System.Runtime.xml",
        "lib/portable-net40+sl4+win8+wp8+wpa81/System.Threading.Tasks.dll",
        "lib/portable-net40+sl4+win8+wp8+wpa81/System.Threading.Tasks.xml",
        "lib/portable-net40+sl5+win8+wp8+wpa81/ensureRedirect.xml",
        "lib/portable-net40+sl5+win8+wp8+wpa81/System.IO.dll",
        "lib/portable-net40+sl5+win8+wp8+wpa81/System.IO.xml",
        "lib/portable-net40+sl5+win8+wp8+wpa81/System.Runtime.dll",
        "lib/portable-net40+sl5+win8+wp8+wpa81/System.Runtime.xml",
        "lib/portable-net40+sl5+win8+wp8+wpa81/System.Threading.Tasks.dll",
        "lib/portable-net40+sl5+win8+wp8+wpa81/System.Threading.Tasks.xml",
        "lib/portable-net40+win8/ensureRedirect.xml",
        "lib/portable-net40+win8/System.IO.dll",
        "lib/portable-net40+win8/System.IO.xml",
        "lib/portable-net40+win8/System.Runtime.dll",
        "lib/portable-net40+win8/System.Runtime.xml",
        "lib/portable-net40+win8/System.Threading.Tasks.dll",
        "lib/portable-net40+win8/System.Threading.Tasks.xml",
        "lib/portable-net40+win8+wp8+wpa81/ensureRedirect.xml",
        "lib/portable-net40+win8+wp8+wpa81/System.IO.dll",
        "lib/portable-net40+win8+wp8+wpa81/System.IO.xml",
        "lib/portable-net40+win8+wp8+wpa81/System.Runtime.dll",
        "lib/portable-net40+win8+wp8+wpa81/System.Runtime.xml",
        "lib/portable-net40+win8+wp8+wpa81/System.Threading.Tasks.dll",
        "lib/portable-net40+win8+wp8+wpa81/System.Threading.Tasks.xml",
        "lib/portable-net45+win8+wp8+wpa81/_._",
        "lib/portable-net45+win8+wpa81/_._",
        "lib/portable-net451+win81/_._",
        "lib/portable-net451+win81+wpa81/_._",
        "lib/portable-win81+wp81+wpa81/_._",
        "lib/sl4/System.IO.dll",
        "lib/sl4/System.IO.xml",
        "lib/sl4/System.Runtime.dll",
        "lib/sl4/System.Runtime.xml",
        "lib/sl4/System.Threading.Tasks.dll",
        "lib/sl4/System.Threading.Tasks.xml",
        "lib/sl4-windowsphone71/ensureRedirect.xml",
        "lib/sl4-windowsphone71/System.IO.dll",
        "lib/sl4-windowsphone71/System.IO.xml",
        "lib/sl4-windowsphone71/System.Runtime.dll",
        "lib/sl4-windowsphone71/System.Runtime.xml",
        "lib/sl4-windowsphone71/System.Threading.Tasks.dll",
        "lib/sl4-windowsphone71/System.Threading.Tasks.xml",
        "lib/sl5/System.IO.dll",
        "lib/sl5/System.IO.xml",
        "lib/sl5/System.Runtime.dll",
        "lib/sl5/System.Runtime.xml",
        "lib/sl5/System.Threading.Tasks.dll",
        "lib/sl5/System.Threading.Tasks.xml",
        "lib/win8/_._",
        "lib/wp8/_._",
        "lib/wpa81/_._",
        "License-Stable.rtf",
        "Microsoft.Bcl.1.1.9.nupkg",
        "Microsoft.Bcl.1.1.9.nupkg.sha512",
        "Microsoft.Bcl.nuspec"
      ]
    },
    "Microsoft.Bcl.Build/1.0.14": {
      "type": "package",
      "sha512": "cDLKSvNvRa519hplsbSoYqO69TjdDIhfjtKUM0g20/nVROoWsGav9KCI9HtnGjLmdV1+TcUUDhbotcllibjPEA==",
      "files": [
        "content/net40/_._",
        "content/netcore45/_._",
        "content/portable-net40+win8+sl4+wp71+wpa81/_._",
        "content/sl4/_._",
        "content/sl4-windowsphone71/_._",
        "License-Stable.rtf",
        "Microsoft.Bcl.Build.1.0.14.nupkg",
        "Microsoft.Bcl.Build.1.0.14.nupkg.sha512",
        "Microsoft.Bcl.Build.nuspec",
        "tools/Install.ps1",
        "tools/Microsoft.Bcl.Build.targets",
        "tools/Microsoft.Bcl.Build.Tasks.dll",
        "tools/Uninstall.ps1"
      ]
    }
  },
  "projectFileDependencyGroups": {
    "": [
      "AutoMapper >= 4.1.0"
    ],
    ".NETFramework,Version=v4.5": [
      "fx/System.Data "
    ],
    ".NETFramework,Version=v4.0": [
      "fx/System.Data "
    ]
  }
}